lab1/collatz.sv
module collatz( input logic         clk,   // Clock
                  input logic 	    go,    // Load value from n; start iterating
                  input logic  [31:0] n,     // Start value; only read when go = 1
                  output logic [31:0] dout,  // Iteration value: true after go = 1
                  output logic 	    done); // True when dout reaches 1

  logic run;

  always_ff @(posedge clk)
  begin
    if(go)
    begin
      dout <= n;
      done <= (1'b0);
      run <= (n != 32'd1);
    end
    else if (run)
    begin
      logic [31:0] next_dout;

      if (dout[0] == 1'b0)
        next_dout = dout >> 1;
      else
        next_dout = 32'd3 * dout + 1;

      dout <= next_dout;

      if (next_dout == 32'd1)
      begin
        done <= 1'b1;
        run <= 1'b0;
      end
    end
  end

endmodule

lab1/collatz.vcd
$version Generated by VerilatedVcd $end
$date Mon Feb  9 15:31:19 2026
 $end
$timescale   1ns $end

 $scope module TOP $end
  $var wire  1 3 clk $end
  $var wire  1 S done $end
  $var wire 32 K dout [31:0] $end
  $var wire  1 ; go $end
  $var wire 32 C n [31:0] $end
  $scope module collatz $end
   $var wire  1 3 clk $end
   $var wire  1 S done $end
   $var wire 32 K dout [31:0] $end
   $var wire  1 ; go $end
   $var wire 32 C n [31:0] $end
   $var wire  1 # run $end
   $scope module unnamedblk1 $end
    $var wire 32 + next_dout [31:0] $end
   $upscope $end
  $upscope $end
 $upscope $end
$enddefinitions $end


#0
0#
b00000000000000000000000000000000 +
03
0;
b00000000000000000000000000000111 C
b00000000000000000000000000000000 K
0S
#10
13
#20
03
1;
#30
1#
13
b00000000000000000000000000000111 K
#40
03
#50
13
#60
03
0;
#70
b00000000000000000000000000010110 +
13
b00000000000000000000000000010110 K
#80
03
#90
b00000000000000000000000000001011 +
13
b00000000000000000000000000001011 K
#100
03
#110
b00000000000000000000000000100010 +
13
b00000000000000000000000000100010 K
#120
03
#130
b00000000000000000000000000010001 +
13
b00000000000000000000000000010001 K
#140
03
#150
b00000000000000000000000000110100 +
13
b00000000000000000000000000110100 K
#160
03
#170
b00000000000000000000000000011010 +
13
b00000000000000000000000000011010 K
#180
03
#190
b00000000000000000000000000001101 +
13
b00000000000000000000000000001101 K
#200
03
#210
b00000000000000000000000000101000 +
13
b00000000000000000000000000101000 K
#220
03
#230
b00000000000000000000000000010100 +
13
b00000000000000000000000000010100 K
#240
03
#250
b00000000000000000000000000001010 +
13
b00000000000000000000000000001010 K
#260
03
#270
b00000000000000000000000000000101 +
13
b00000000000000000000000000000101 K
#280
03
#290
b00000000000000000000000000010000 +
13
b00000000000000000000000000010000 K
#300
03
#310
b00000000000000000000000000001000 +
13
b00000000000000000000000000001000 K
#320
03
#330
b00000000000000000000000000000100 +
13
b00000000000000000000000000000100 K
#340
03
#350
b00000000000000000000000000000010 +
13
b00000000000000000000000000000010 K
#360
03
#370
0#
b00000000000000000000000000000001 +
13
b00000000000000000000000000000001 K
1S
